<?xml version="1.0" encoding="UTF-8"?>
<root><synset name="Verbo" id="0" nSelect="0" countSub="0" /><synset name="Substantivo" id="0" nSelect="0" countSub="115"><synset name="{entity}" id="1740" nSelect="0" countSub="114"><synset name="{abstraction, abstract entity}" id="2137" nSelect="0" countSub="70"><synset name="{psychological feature}" id="23100" nSelect="0" countSub="16"><synset name="{event}" id="29378" nSelect="0" countSub="12"><synset name="{act, deed, human action, human activity}" id="30358" nSelect="0" countSub="12"><synset name="{action}" id="37396" nSelect="0" countSub="5"><synset name="{choice, selection, option, pick}" id="161243" nSelect="0" countSub="5"><synset name="{casting}" id="161603" nSelect="0" countSub="0" /><synset name="{coloration, colouration}" id="161739" nSelect="0" countSub="0" /><synset name="{sampling}" id="161888" nSelect="0" countSub="0" /><synset name="{decision, determination, conclusion}" id="162632" nSelect="0" countSub="0" /><synset name="{volition, willing}" id="163047" nSelect="0" countSub="0" /><synset name="{election}" id="180962" nSelect="0" countSub="0" /><synset name="{vote, ballot, voting, balloting}" id="183505" nSelect="5" countSub="5"><synset name="{block vote}" id="183995" nSelect="0" countSub="0" /><synset name="{secret ballot}" id="184362" nSelect="0" countSub="0" /><synset name="{split ticket}" id="184501" nSelect="0" countSub="0" /><synset name="{straight ticket}" id="184652" nSelect="0" countSub="0" /><synset name="{multiple voting}" id="184802" nSelect="0" countSub="0" /><synset name="{casting vote}" id="184981" nSelect="0" countSub="0" /><synset name="{veto}" id="209546" nSelect="0" countSub="0" /><synset name="{write-in}" id="209789" nSelect="0" countSub="0" /></synset></synset></synset><synset name="{activity}" id="407535" nSelect="0" countSub="7"><synset name="{wrongdoing, wrongful conduct, misconduct, actus reus}" id="732746" nSelect="0" countSub="7"><synset name="{transgression, evildoing}" id="745005" nSelect="0" countSub="7"><synset name="{crime, offense, criminal offense, criminal offence, offence, law-breaking}" id="766234" nSelect="0" countSub="7"><synset name="{barratry}" id="765343" nSelect="0" countSub="0" /><synset name="{capital offense}" id="768353" nSelect="0" countSub="0" /><synset name="{cybercrime}" id="768483" nSelect="0" countSub="0" /><synset name="{felony}" id="768701" nSelect="0" countSub="0" /><synset name="{forgery}" id="768921" nSelect="0" countSub="0" /><synset name="{fraud}" id="769092" nSelect="0" countSub="0" /><synset name="{Had crime}" id="769695" nSelect="0" countSub="0" /><synset name="{hijack, highjack}" id="769944" nSelect="0" countSub="0" /><synset name="{mayhem}" id="770151" nSelect="0" countSub="0" /><synset name="{misdemeanor, misdemeanour, infraction, violation, infringement}" id="770270" nSelect="0" countSub="0" /><synset name="{perpetration, commission, committal}" id="773235" nSelect="0" countSub="0" /><synset name="{Tazir crime}" id="774506" nSelect="0" countSub="0" /><synset name="{statutory offense, statutory offence, regulatory offense, regulatory offence}" id="774796" nSelect="0" countSub="0" /><synset name="{thuggery}" id="775006" nSelect="0" countSub="0" /><synset name="{treason, high treason, lese majesty}" id="782072" nSelect="0" countSub="0" /><synset name="{vice crime}" id="782241" nSelect="0" countSub="0" /><synset name="{victimless crime}" id="782338" nSelect="0" countSub="0" /><synset name="{war crime}" id="782518" nSelect="0" countSub="0" /><synset name="{attack, attempt}" id="773814" nSelect="7" countSub="7"><synset name="{assault}" id="767826" nSelect="0" countSub="0" /></synset></synset></synset></synset></synset></synset></synset><synset name="{cognition, knowledge, noesis}" id="23271" nSelect="0" countSub="4"><synset name="{content, cognitive content, mental object}" id="5809192" nSelect="0" countSub="4"><synset name="{goal, end}" id="5980875" nSelect="0" countSub="4"><synset name="{bourn, bourne}" id="5981546" nSelect="0" countSub="0" /><synset name="{end-all}" id="5981648" nSelect="0" countSub="0" /><synset name="{destination, terminus}" id="5981768" nSelect="0" countSub="0" /><synset name="{no-goal}" id="5982024" nSelect="0" countSub="0" /><synset name="{purpose, intent, intention, aim, design}" id="5982152" nSelect="0" countSub="0" /><synset name="{intention}" id="5982720" nSelect="0" countSub="0" /><synset name="{aim, object, objective, target}" id="5981230" nSelect="4" countSub="4"><synset name="{grail}" id="5981936" nSelect="0" countSub="0" /><synset name="{business}" id="5983801" nSelect="0" countSub="0" /><synset name="{point}" id="5984066" nSelect="0" countSub="0" /><synset name="{thing}" id="5984182" nSelect="0" countSub="0" /></synset></synset></synset></synset></synset><synset name="{measure, quantity, amount}" id="33615" nSelect="0" countSub="8"><synset name="{fundamental quantity, fundamental measure}" id="13575869" nSelect="0" countSub="8"><synset name="{time period, period of time, period}" id="15113229" nSelect="0" countSub="8"><synset name="{calendar day, civil day}" id="15157041" nSelect="0" countSub="4"><synset name="{day of the week}" id="15163005" nSelect="0" countSub="4"><synset name="{weekday}" id="15163157" nSelect="0" countSub="4"><synset name="{workday, working day, work day}" id="15136923" nSelect="0" countSub="0" /><synset name="{feria}" id="15163408" nSelect="0" countSub="0" /><synset name="{Monday, Mon}" id="15163979" nSelect="0" countSub="0" /><synset name="{Tuesday, Tues}" id="15164105" nSelect="0" countSub="0" /><synset name="{Thursday, Th}" id="15164354" nSelect="0" countSub="0" /><synset name="{Friday, Fri}" id="15164463" nSelect="0" countSub="0" /><synset name="{Saturday, Sabbatum, Sat}" id="15164570" nSelect="0" countSub="0" /><synset name="{Wednesday, Midweek, Wed}" id="15164233" nSelect="4" countSub="4" /></synset></synset></synset><synset name="{trial period, test period}" id="15115926" nSelect="0" countSub="0" /><synset name="{time frame}" id="15116095" nSelect="0" countSub="0" /><synset name="{hours}" id="15117516" nSelect="0" countSub="0" /><synset name="{downtime}" id="15117621" nSelect="0" countSub="0" /><synset name="{uptime}" id="15117809" nSelect="0" countSub="0" /><synset name="{work time}" id="15118228" nSelect="0" countSub="0" /><synset name="{time off}" id="15118453" nSelect="0" countSub="0" /><synset name="{bout}" id="15119072" nSelect="0" countSub="0" /><synset name="{hospitalization}" id="15119185" nSelect="0" countSub="0" /><synset name="{travel time}" id="15119374" nSelect="0" countSub="0" /><synset name="{times}" id="15120346" nSelect="0" countSub="0" /><synset name="{time}" id="15122231" nSelect="0" countSub="0" /><synset name="{elapsed time}" id="15131123" nSelect="0" countSub="0" /><synset name="{duration, continuance}" id="15133621" nSelect="0" countSub="0" /><synset name="{week, calendar week}" id="15136147" nSelect="0" countSub="0" /><synset name="{midweek}" id="15136342" nSelect="0" countSub="0" /><synset name="{field day}" id="15138809" nSelect="0" countSub="0" /><synset name="{life, lifetime, life-time, lifespan}" id="15140405" nSelect="0" countSub="0" /><synset name="{life}" id="15140744" nSelect="0" countSub="0" /><synset name="{life}" id="15140892" nSelect="0" countSub="0" /><synset name="{millennium, millenary}" id="15141213" nSelect="0" countSub="0" /><synset name="{bimillennium, bimillenary}" id="15141375" nSelect="0" countSub="0" /><synset name="{occupation}" id="15141486" nSelect="0" countSub="0" /><synset name="{past}" id="15141693" nSelect="0" countSub="0" /><synset name="{shelf life}" id="15141894" nSelect="0" countSub="0" /><synset name="{puerperium}" id="15142568" nSelect="0" countSub="0" /><synset name="{lactation}" id="15142836" nSelect="0" countSub="0" /><synset name="{time of life}" id="15144371" nSelect="0" countSub="0" /><synset name="{festival}" id="15162388" nSelect="0" countSub="0" /><synset name="{day, daytime, daylight}" id="15164957" nSelect="0" countSub="0" /><synset name="{morning, morn, morning time, forenoon}" id="15165289" nSelect="0" countSub="0" /><synset name="{night, nighttime, dark}" id="15167027" nSelect="0" countSub="0" /><synset name="{night}" id="15167349" nSelect="0" countSub="0" /><synset name="{night}" id="15167474" nSelect="0" countSub="0" /><synset name="{night}" id="15167577" nSelect="0" countSub="0" /><synset name="{eve}" id="15167778" nSelect="0" countSub="0" /><synset name="{evening}" id="15167906" nSelect="0" countSub="0" /><synset name="{week, hebdomad}" id="15169873" nSelect="0" countSub="0" /><synset name="{fortnight, two weeks}" id="15170331" nSelect="0" countSub="0" /><synset name="{weekend}" id="15170504" nSelect="0" countSub="0" /><synset name="{Indian summer, Saint Martin's summer}" id="15185996" nSelect="0" countSub="0" /><synset name="{year}" id="15201505" nSelect="0" countSub="0" /><synset name="{school, schooltime, school day}" id="15203229" nSelect="0" countSub="0" /><synset name="{year}" id="15204297" nSelect="0" countSub="0" /><synset name="{semester}" id="15204485" nSelect="0" countSub="0" /><synset name="{bimester}" id="15204609" nSelect="0" countSub="0" /><synset name="{Olympiad}" id="15204720" nSelect="0" countSub="0" /><synset name="{lustrum}" id="15204907" nSelect="0" countSub="0" /><synset name="{decade, decennary, decennium}" id="15204983" nSelect="0" countSub="0" /><synset name="{century}" id="15205532" nSelect="0" countSub="0" /><synset name="{quadrennium}" id="15205719" nSelect="0" countSub="0" /><synset name="{quinquennium}" id="15205799" nSelect="0" countSub="0" /><synset name="{half-century}" id="15206097" nSelect="0" countSub="0" /><synset name="{quarter-century}" id="15206195" nSelect="0" countSub="0" /><synset name="{quarter}" id="15206590" nSelect="0" countSub="0" /><synset name="{phase of the moon}" id="15206744" nSelect="0" countSub="0" /><synset name="{day}" id="15208540" nSelect="0" countSub="0" /><synset name="{calendar month, month}" id="15209413" nSelect="0" countSub="0" /><synset name="{mid-January}" id="15210383" nSelect="0" countSub="0" /><synset name="{mid-February}" id="15210765" nSelect="0" countSub="0" /><synset name="{mid-March}" id="15211090" nSelect="0" countSub="0" /><synset name="{mid-April}" id="15211385" nSelect="0" countSub="0" /><synset name="{mid-May}" id="15211711" nSelect="0" countSub="0" /><synset name="{mid-June}" id="15212070" nSelect="0" countSub="0" /><synset name="{mid-July}" id="15212358" nSelect="0" countSub="0" /><synset name="{mid-August}" id="15212638" nSelect="0" countSub="0" /><synset name="{mid-September}" id="15213008" nSelect="0" countSub="0" /><synset name="{mid-October}" id="15213303" nSelect="0" countSub="0" /><synset name="{mid-November}" id="15213669" nSelect="0" countSub="0" /><synset name="{mid-December}" id="15213963" nSelect="0" countSub="0" /><synset name="{time limit}" id="15224156" nSelect="0" countSub="0" /><synset name="{term}" id="15224486" nSelect="0" countSub="0" /><synset name="{trimester}" id="15226732" nSelect="0" countSub="0" /><synset name="{hour}" id="15228910" nSelect="0" countSub="0" /><synset name="{silly season}" id="15230617" nSelect="0" countSub="0" /><synset name="{Golden Age}" id="15230790" nSelect="0" countSub="0" /><synset name="{silver age}" id="15231031" nSelect="0" countSub="0" /><synset name="{bronze age}" id="15231263" nSelect="0" countSub="0" /><synset name="{iron age}" id="15231634" nSelect="0" countSub="0" /><synset name="{great year, Platonic year}" id="15233614" nSelect="0" countSub="0" /><synset name="{regulation time}" id="15233778" nSelect="0" countSub="0" /><synset name="{overtime, extra time}" id="15233989" nSelect="0" countSub="0" /><synset name="{season, time of year}" id="15236475" nSelect="0" countSub="0" /><synset name="{dog days, canicule, canicular days}" id="15237567" nSelect="0" countSub="0" /><synset name="{midwinter}" id="15238074" nSelect="0" countSub="0" /><synset name="{season}" id="15239292" nSelect="0" countSub="0" /><synset name="{season}" id="15239579" nSelect="0" countSub="0" /><synset name="{long time, age, years}" id="15242955" nSelect="0" countSub="0" /><synset name="{long run, long haul}" id="15243351" nSelect="0" countSub="0" /><synset name="{drought, drouth}" id="15244505" nSelect="0" countSub="0" /><synset name="{era, epoch}" id="15248564" nSelect="0" countSub="0" /><synset name="{generation}" id="15249636" nSelect="0" countSub="0" /><synset name="{prehistory, prehistoric culture}" id="15254550" nSelect="0" countSub="0" /><synset name="{reign}" id="15260964" nSelect="0" countSub="0" /><synset name="{run}" id="15262120" nSelect="0" countSub="0" /><synset name="{youth, early days}" id="15266034" nSelect="0" countSub="0" /><synset name="{dawn}" id="15267945" nSelect="0" countSub="0" /><synset name="{evening}" id="15268094" nSelect="0" countSub="0" /><synset name="{time}" id="15270431" nSelect="0" countSub="0" /><synset name="{sleep, nap}" id="15273626" nSelect="0" countSub="0" /><synset name="{lease, term of a contract}" id="15274863" nSelect="0" countSub="0" /><synset name="{half life, half-life}" id="15275094" nSelect="0" countSub="0" /><synset name="{tide, lunar time period}" id="15275727" nSelect="0" countSub="0" /><synset name="{phase, stage}" id="15290337" nSelect="0" countSub="0" /><synset name="{multistage}" id="15291110" nSelect="0" countSub="0" /><synset name="{watch}" id="15292502" nSelect="0" countSub="0" /><synset name="{peacetime}" id="15293227" nSelect="0" countSub="0" /><synset name="{wartime}" id="15293328" nSelect="0" countSub="0" /><synset name="{enlistment, hitch, term of enlistment, tour of duty, duty tour, tour}" id="15293590" nSelect="0" countSub="0" /><synset name="{honeymoon}" id="15293788" nSelect="0" countSub="0" /><synset name="{indiction}" id="15293931" nSelect="0" countSub="0" /><synset name="{prohibition, prohibition era}" id="15294382" nSelect="0" countSub="0" /><synset name="{incubation period}" id="15294607" nSelect="0" countSub="0" /><synset name="{rainy day}" id="15294745" nSelect="0" countSub="0" /><synset name="{novitiate, noviciate}" id="15294884" nSelect="0" countSub="0" /><synset name="{flower, prime, peak, heyday, bloom, blossom, efflorescence, flush}" id="15295045" nSelect="0" countSub="0" /><synset name="{running time}" id="15295778" nSelect="0" countSub="0" /><synset name="{clotting time}" id="15296920" nSelect="0" countSub="0" /><synset name="{air alert}" id="15297859" nSelect="0" countSub="0" /><synset name="{question time}" id="15298507" nSelect="0" countSub="0" /><synset name="{real time}" id="15298695" nSelect="0" countSub="0" /><synset name="{real time}" id="15298852" nSelect="0" countSub="0" /><synset name="{study hall}" id="15299225" nSelect="0" countSub="0" /><synset name="{usance}" id="15299585" nSelect="0" countSub="0" /><synset name="{window}" id="15299783" nSelect="0" countSub="0" /><synset name="{year, twelvemonth, yr}" id="15203791" nSelect="4" countSub="4"><synset name="{church year, Christian year}" id="15173064" nSelect="0" countSub="0" /><synset name="{Holy Year}" id="15181556" nSelect="0" countSub="0" /><synset name="{New Year}" id="15182319" nSelect="0" countSub="0" /><synset name="{common year, 365 days}" id="15202131" nSelect="0" countSub="0" /><synset name="{leap year, intercalary year, 366 days, bissextile year}" id="15202230" nSelect="0" countSub="0" /><synset name="{off year}" id="15202424" nSelect="0" countSub="0" /><synset name="{off year}" id="15202532" nSelect="0" countSub="0" /><synset name="{calendar year, civil year}" id="15202634" nSelect="0" countSub="0" /><synset name="{fiscal year, financial year}" id="15203120" nSelect="0" countSub="0" /><synset name="{annum}" id="15204201" nSelect="0" countSub="0" /><synset name="{year of grace}" id="15249458" nSelect="0" countSub="0" /><synset name="{Y2K}" id="15249547" nSelect="0" countSub="0" /></synset></synset></synset></synset><synset name="{group, grouping}" id="31264" nSelect="0" countSub="28"><synset name="{social group}" id="7950920" nSelect="0" countSub="28"><synset name="{organization, organisation}" id="8008335" nSelect="5" countSub="28"><synset name="{polity}" id="8050385" nSelect="0" countSub="11"><synset name="{government, authorities, regime}" id="8050678" nSelect="11" countSub="11"><synset name="{authoritarian state, authoritarian regime}" id="8051384" nSelect="0" countSub="0" /><synset name="{bureaucracy}" id="8051565" nSelect="0" countSub="0" /><synset name="{ancien regime}" id="8051739" nSelect="0" countSub="0" /><synset name="{court, royal court}" id="8051946" nSelect="0" countSub="0" /><synset name="{Downing Street}" id="8052330" nSelect="0" countSub="0" /><synset name="{empire}" id="8052413" nSelect="0" countSub="0" /><synset name="{federal government}" id="8052549" nSelect="0" countSub="0" /><synset name="{government-in-exile}" id="8052690" nSelect="0" countSub="0" /><synset name="{local government}" id="8052874" nSelect="0" countSub="0" /><synset name="{military government, stratocracy}" id="8053003" nSelect="0" countSub="0" /><synset name="{palace}" id="8053121" nSelect="0" countSub="0" /><synset name="{papacy, pontificate}" id="8053260" nSelect="0" countSub="0" /><synset name="{puppet government, puppet state, pupet regime}" id="8178321" nSelect="0" countSub="0" /><synset name="{state}" id="8178547" nSelect="0" countSub="0" /><synset name="{state government}" id="8226018" nSelect="0" countSub="0" /><synset name="{totalitarian state, totalitation regime}" id="8226127" nSelect="0" countSub="0" /></synset></synset><synset name="{unit, social unit}" id="8189659" nSelect="0" countSub="12"><synset name="{political unit, political entity}" id="8359949" nSelect="0" countSub="8"><synset name="{Holy Roman Empire}" id="8169677" nSelect="0" countSub="0" /><synset name="{union}" id="8304895" nSelect="0" countSub="0" /><synset name="{Palestine National Authority, Palestinian National Authority, Palestine Authority}" id="8320923" nSelect="0" countSub="0" /><synset name="{cell, cadre}" id="8358594" nSelect="0" countSub="0" /><synset name="{amphictyony}" id="8360248" nSelect="0" countSub="0" /><synset name="{lunatic fringe}" id="8360430" nSelect="0" countSub="0" /><synset name="{revolutionary group}" id="8360540" nSelect="0" countSub="0" /><synset name="{lobby, pressure group, third house}" id="8375526" nSelect="0" countSub="0" /><synset name="{state, nation, country, land, commonwealth, res publica, body politic}" id="8168978" nSelect="8" countSub="8"><synset name="{commonwealth country}" id="8166931" nSelect="0" countSub="0" /><synset name="{developing country}" id="8167046" nSelect="0" countSub="0" /><synset name="{Dominion}" id="8167249" nSelect="0" countSub="0" /><synset name="{foreign country}" id="8168367" nSelect="0" countSub="0" /><synset name="{Reich}" id="8169573" nSelect="0" countSub="0" /><synset name="{rogue state, renegade state, rogue nation}" id="8170374" nSelect="0" countSub="0" /><synset name="{suzerain}" id="8170535" nSelect="0" countSub="0" /><synset name="{sea power}" id="8177487" nSelect="0" countSub="0" /><synset name="{world power, major power, great power, power, superpower}" id="8177592" nSelect="0" countSub="0" /><synset name="{city state, city-state}" id="8177958" nSelect="0" countSub="0" /><synset name="{ally}" id="8305942" nSelect="0" countSub="0" /></synset></synset><synset name="{administrative unit, administrative body}" id="8077292" nSelect="0" countSub="4"><synset name="{Inland Revenue, IR}" id="8143486" nSelect="0" countSub="0" /><synset name="{Ordnance Survey}" id="8153874" nSelect="0" countSub="0" /><synset name="{division}" id="8220714" nSelect="0" countSub="0" /><synset name="{United Nations agency, UN agency}" id="8299493" nSelect="0" countSub="0" /><synset name="{council}" id="8310949" nSelect="0" countSub="0" /><synset name="{secretariat, secretariate}" id="8324274" nSelect="0" countSub="0" /><synset name="{committee, commission}" id="8324514" nSelect="0" countSub="0" /><synset name="{intelligence, intelligence service, intelligence agency}" id="8339454" nSelect="0" countSub="0" /><synset name="{international law enforcement agency}" id="8344551" nSelect="0" countSub="0" /><synset name="{redevelopment authority}" id="8353244" nSelect="0" countSub="0" /><synset name="{regulatory agency, regulatory authority}" id="8353406" nSelect="0" countSub="0" /><synset name="{weather bureau}" id="8353734" nSelect="0" countSub="0" /><synset name="{placement office, placement center}" id="8354523" nSelect="0" countSub="0" /><synset name="{child welfare agency, child welfare service}" id="8423840" nSelect="0" countSub="0" /><synset name="{Russian agency}" id="8485830" nSelect="0" countSub="0" /><synset name="{agency, federal agency, government agency, bureau, office, authority}" id="8337324" nSelect="4" countSub="4"><synset name="{executive agency}" id="8123696" nSelect="0" countSub="0" /><synset name="{Food and Drug Administration, FDA}" id="8124256" nSelect="0" countSub="0" /><synset name="{Center for Disease Control and Prevention, CDC}" id="8124649" nSelect="0" countSub="0" /><synset name="{Counterterrorist Center, CTC}" id="8125420" nSelect="0" countSub="0" /><synset name="{Nonproliferation Center, NPC}" id="8125722" nSelect="0" countSub="0" /><synset name="{Bureau of the Census, Census Bureau}" id="8129621" nSelect="0" countSub="0" /><synset name="{National Oceanic and Atmospheric Administration, NOAA}" id="8129883" nSelect="0" countSub="0" /><synset name="{National Climatic Data Center, NCDC}" id="8130292" nSelect="0" countSub="0" /><synset name="{National Weather Service}" id="8130476" nSelect="0" countSub="0" /><synset name="{Technology Administration}" id="8130712" nSelect="0" countSub="0" /><synset name="{National Institute of Standards and Technology, NIST}" id="8131005" nSelect="0" countSub="0" /><synset name="{National Technical Information Service, NTIS}" id="8131254" nSelect="0" countSub="0" /><synset name="{Defense Advanced Research Projects Agency, DARPA}" id="8132046" nSelect="0" countSub="0" /><synset name="{Department of Defense Laboratory System, LABLINK}" id="8132323" nSelect="0" countSub="0" /><synset name="{Department of Energy Intelligence, DOEI}" id="8133189" nSelect="0" countSub="0" /><synset name="{United States Public Health Service, PHS}" id="8133855" nSelect="0" countSub="0" /><synset name="{National Institutes of Health, NIH}" id="8134081" nSelect="0" countSub="0" /><synset name="{Bureau of Justice Assistance, BJA}" id="8135770" nSelect="0" countSub="0" /><synset name="{Bureau of Justice Statistics, BJS}" id="8136027" nSelect="0" countSub="0" /><synset name="{Immigration and Naturalization Service, INS}" id="8136502" nSelect="0" countSub="0" /><synset name="{United States Border Patrol, US Border Patrol}" id="8136767" nSelect="0" countSub="0" /><synset name="{Bureau of Diplomatic Security, DS}" id="8138259" nSelect="0" countSub="0" /><synset name="{Foreign Service}" id="8138466" nSelect="0" countSub="0" /><synset name="{Bureau of Intelligence and Research, INR}" id="8138686" nSelect="0" countSub="0" /><synset name="{United States Fish and Wildlife Service, US Fish and Wildlife Service, FWS}" id="8139270" nSelect="0" countSub="0" /><synset name="{National Park Service}" id="8139637" nSelect="0" countSub="0" /><synset name="{Financial Management Service}" id="8140506" nSelect="0" countSub="0" /><synset name="{Office of Intelligence Support, OIS}" id="8140767" nSelect="0" countSub="0" /><synset name="{Comptroller of the Currency}" id="8142801" nSelect="0" countSub="0" /><synset name="{Bureau of Customs, Customs Bureau, Customs Service, USCB}" id="8142972" nSelect="0" countSub="0" /><synset name="{Bureau of Engraving and Printing}" id="8143163" nSelect="0" countSub="0" /><synset name="{Internal Revenue Service, IRS}" id="8143321" nSelect="0" countSub="0" /><synset name="{Federal Aviation Agency, FAA}" id="8143926" nSelect="0" countSub="0" /><synset name="{Transportation Security Administration, TSA}" id="8144308" nSelect="0" countSub="0" /><synset name="{Government Accounting Office, GAO, United States Government Accounting Office}" id="8162245" nSelect="0" countSub="0" /><synset name="{United States Navy, US Navy, USN, Navy}" id="8191987" nSelect="0" countSub="0" /><synset name="{United States Coast Guard, U. S. Coast Guard, US Coast Guard}" id="8192557" nSelect="0" countSub="0" /><synset name="{Naval Air Warfare Center Weapons Division, NAWCWPNS}" id="8193212" nSelect="0" countSub="0" /><synset name="{Naval Special Warfare, NSW}" id="8193448" nSelect="0" countSub="0" /><synset name="{Naval Surface Warfare Center, NSWC}" id="8193645" nSelect="0" countSub="0" /><synset name="{Naval Underwater Warfare Center, NUWC}" id="8193854" nSelect="0" countSub="0" /><synset name="{Office of Naval Intelligence, ONI}" id="8194266" nSelect="0" countSub="0" /><synset name="{Marine Corps Intelligence Activity, MCIA}" id="8194546" nSelect="0" countSub="0" /><synset name="{United States Air Force, U. S. Air Force, US Air Force, Air Force, USAF}" id="8196230" nSelect="0" countSub="0" /><synset name="{Air Force Intelligence Surveillance and Reconnaissance, Air Force ISR, AFISR}" id="8197386" nSelect="0" countSub="0" /><synset name="{independent agency}" id="8338847" nSelect="0" countSub="0" /><synset name="{Advanced Research and Development Activity, ARDA}" id="8340753" nSelect="0" countSub="0" /><synset name="{Defense Logistics Agency}" id="8341330" nSelect="0" countSub="0" /><synset name="{Defense Reutilization and Marketing Service, DRMS}" id="8341551" nSelect="0" countSub="0" /><synset name="{Defense Technical Information Center, DTIC}" id="8341798" nSelect="0" countSub="0" /><synset name="{law enforcement agency}" id="8348815" nSelect="0" countSub="0" /><synset name="{Occupational Safety and Health Administration, OSHA}" id="8349138" nSelect="0" countSub="0" /><synset name="{organ}" id="8349350" nSelect="0" countSub="0" /><synset name="{Patent and Trademark Office Database, Patent Office}" id="8349681" nSelect="0" countSub="0" /><synset name="{United States Government Printing Office, US Government Printing Office, Government Printing Office, GPO}" id="8356573" nSelect="0" countSub="0" /><synset name="{National Guard Bureau, NGB}" id="8391696" nSelect="0" countSub="0" /><synset name="{United States Army, US Army, U. S. Army, Army, USA}" id="8394922" nSelect="0" countSub="0" /><synset name="{Army Intelligence, AI}" id="8395682" nSelect="0" countSub="0" /><synset name="{Ballistic Missile Defense Organization, BMDO}" id="8395991" nSelect="0" countSub="0" /><synset name="{Defense Information Systems Agency, DISA}" id="8396207" nSelect="0" countSub="0" /><synset name="{National Geospatial-Intelligence Agency, NGA}" id="8396537" nSelect="0" countSub="0" /><synset name="{Casualty Care Research Center, CCRC}" id="8396760" nSelect="0" countSub="0" /><synset name="{Federal Housing Administration, FHA}" id="8423634" nSelect="0" countSub="0" /><synset name="{local authority}" id="8482577" nSelect="0" countSub="0" /></synset></synset></synset><synset name="{adhocracy}" id="8009239" nSelect="0" countSub="0" /><synset name="{affiliate}" id="8009478" nSelect="0" countSub="0" /><synset name="{bureaucracy}" id="8009659" nSelect="0" countSub="0" /><synset name="{nongovernmental organization, NGO}" id="8009834" nSelect="0" countSub="0" /><synset name="{Tammany Hall, Tammany Society, Tammany}" id="8048042" nSelect="0" countSub="0" /><synset name="{fiefdom}" id="8048625" nSelect="0" countSub="0" /><synset name="{line of defense, line of defence}" id="8048743" nSelect="0" countSub="0" /><synset name="{line organization, line organisation}" id="8048948" nSelect="0" countSub="0" /><synset name="{association}" id="8049401" nSelect="0" countSub="0" /><synset name="{quango, quasi-NGO}" id="8050484" nSelect="0" countSub="0" /><synset name="{institution, establishment}" id="8053576" nSelect="0" countSub="0" /><synset name="{enterprise}" id="8056231" nSelect="0" countSub="0" /><synset name="{defense, defence, defense force, defence force}" id="8064130" nSelect="0" countSub="0" /><synset name="{establishment}" id="8075847" nSelect="0" countSub="0" /><synset name="{fire brigade, fire company}" id="8121394" nSelect="0" countSub="0" /><synset name="{company, troupe}" id="8187033" nSelect="0" countSub="0" /><synset name="{Peace Corps}" id="8195636" nSelect="0" countSub="0" /><synset name="{force, personnel}" id="8208016" nSelect="0" countSub="0" /><synset name="{union, labor union, trade union, trades union, brotherhood}" id="8233056" nSelect="0" countSub="0" /><synset name="{musical organization, musical organisation, musical group}" id="8246613" nSelect="0" countSub="0" /><synset name="{party, political party}" id="8256968" nSelect="0" countSub="0" /><synset name="{machine, political machine}" id="8264583" nSelect="0" countSub="0" /><synset name="{machine}" id="8264759" nSelect="0" countSub="0" /><synset name="{professional organization, professional organisation}" id="8266070" nSelect="0" countSub="0" /><synset name="{alliance, coalition, alignment, alinement}" id="8293982" nSelect="0" countSub="0" /><synset name="{federation}" id="8303504" nSelect="0" countSub="0" /><synset name="{hierarchy, power structure, pecking order}" id="8376051" nSelect="0" countSub="0" /><synset name="{deputation, commission, delegation, delegacy, mission}" id="8402442" nSelect="0" countSub="0" /><synset name="{Girl Scouts}" id="8471185" nSelect="0" countSub="0" /><synset name="{blue}" id="8480847" nSelect="0" countSub="0" /><synset name="{grey, gray}" id="8481009" nSelect="0" countSub="0" /><synset name="{host}" id="8481184" nSelect="0" countSub="0" /><synset name="{pool}" id="8481369" nSelect="0" countSub="0" /></synset><synset name="{body}" id="7965085" nSelect="0" countSub="0" /><synset name="{society}" id="7966140" nSelect="0" countSub="0" /><synset name="{minority}" id="7966570" nSelect="0" countSub="0" /><synset name="{sector}" id="7966719" nSelect="0" countSub="0" /><synset name="{interest, interest group}" id="7968702" nSelect="0" countSub="0" /><synset name="{kin, kin group, kinship group, kindred, clan, tribe}" id="7969695" nSelect="0" countSub="0" /><synset name="{kith}" id="7970301" nSelect="0" countSub="0" /><synset name="{fringe}" id="7974850" nSelect="0" countSub="0" /><synset name="{gathering, assemblage}" id="7975026" nSelect="0" countSub="0" /><synset name="{congregation, fold, faithful}" id="7991364" nSelect="0" countSub="0" /><synset name="{phylum}" id="8103635" nSelect="0" countSub="0" /><synset name="{force}" id="8207863" nSelect="0" countSub="0" /><synset name="{platoon}" id="8215044" nSelect="0" countSub="0" /><synset name="{revolving door}" id="8240022" nSelect="0" countSub="0" /><synset name="{set, circle, band, lot}" id="8240169" nSelect="0" countSub="0" /><synset name="{organized crime, gangland, gangdom}" id="8245172" nSelect="0" countSub="0" /><synset name="{subculture}" id="8288753" nSelect="0" countSub="0" /><synset name="{nonalignment, nonalinement}" id="8294395" nSelect="0" countSub="0" /><synset name="{political system, form of government}" id="8367880" nSelect="0" countSub="0" /><synset name="{moiety}" id="8372299" nSelect="0" countSub="0" /><synset name="{tribe, folk}" id="8372411" nSelect="0" countSub="0" /><synset name="{movement, social movement, front}" id="8464601" nSelect="0" countSub="0" /><synset name="{Jewry}" id="8479095" nSelect="0" countSub="0" /><synset name="{wing}" id="8486306" nSelect="0" countSub="0" /></synset></synset><synset name="{attribute}" id="24264" nSelect="0" countSub="18"><synset name="{state}" id="24720" nSelect="0" countSub="18"><synset name="{condition, status}" id="13920835" nSelect="0" countSub="9"><synset name="{difficulty}" id="14408086" nSelect="0" countSub="9"><synset name="{bitch}" id="14408519" nSelect="0" countSub="0" /><synset name="{predicament, quandary, plight}" id="14408646" nSelect="0" countSub="0" /><synset name="{rattrap}" id="14409285" nSelect="0" countSub="0" /><synset name="{pinch}" id="14409371" nSelect="0" countSub="0" /><synset name="{fix, hole, jam, mess, muddle, pickle, kettle of fish}" id="14409489" nSelect="0" countSub="0" /><synset name="{hard time, rough sledding}" id="14409880" nSelect="0" countSub="0" /><synset name="{stress, strain}" id="14410089" nSelect="0" countSub="0" /><synset name="{mire}" id="14410365" nSelect="0" countSub="0" /><synset name="{situation}" id="14411243" nSelect="0" countSub="4"><synset name="{conflict of interest}" id="13933391" nSelect="0" countSub="0" /><synset name="{crunch}" id="13934070" nSelect="0" countSub="0" /><synset name="{hornet's nest, hornets' nest}" id="13935572" nSelect="0" countSub="0" /><synset name="{hot potato}" id="13935910" nSelect="0" countSub="0" /><synset name="{how-do-you-do, how-d'ye-do}" id="13936030" nSelect="0" countSub="0" /><synset name="{imbroglio, embroilment}" id="13936153" nSelect="0" countSub="0" /><synset name="{Mexican standoff}" id="13936557" nSelect="0" countSub="0" /><synset name="{nightmare, incubus}" id="13936676" nSelect="0" countSub="0" /><synset name="{no-win situation}" id="13936783" nSelect="0" countSub="0" /><synset name="{pass, strait, straits}" id="13936939" nSelect="0" countSub="0" /><synset name="{purgatory}" id="13937406" nSelect="0" countSub="0" /><synset name="{swamp}" id="13938296" nSelect="0" countSub="0" /><synset name="{time bomb, ticking bomb}" id="13944096" nSelect="0" countSub="0" /><synset name="{tinderbox}" id="13944337" nSelect="0" countSub="0" /><synset name="{urgency}" id="13944516" nSelect="0" countSub="0" /><synset name="{deadlock, dead end, impasse, stalemate, standstill}" id="14015361" nSelect="0" countSub="0" /><synset name="{quicksand}" id="14411772" nSelect="0" countSub="0" /><synset name="{crisis}" id="13933560" nSelect="4" countSub="4"><synset name="{Dunkirk}" id="14032868" nSelect="0" countSub="0" /><synset name="{exigency}" id="14033054" nSelect="0" countSub="0" /><synset name="{juncture, critical point, crossroads}" id="14033185" nSelect="0" countSub="0" /><synset name="{depression, slump, economic crisis}" id="14489113" nSelect="0" countSub="0" /></synset></synset><synset name="{urinary hesitancy}" id="14564519" nSelect="0" countSub="0" /><synset name="{wall}" id="14564779" nSelect="0" countSub="0" /><synset name="{problem, job}" id="14410605" nSelect="5" countSub="5"><synset name="{race problem}" id="14410918" nSelect="0" countSub="0" /><synset name="{balance-of-payments problem}" id="14411079" nSelect="0" countSub="0" /></synset></synset></synset><synset name="{condition}" id="13920429" nSelect="0" countSub="5"><synset name="{fortune, destiny, fate, luck, lot, circumstances, portion}" id="14473222" nSelect="0" countSub="5"><synset name="{misfortune, bad luck, tough luck, ill luck}" id="14475405" nSelect="0" countSub="5"><synset name="{adversity, hardship, hard knocks}" id="14475661" nSelect="0" countSub="5"><synset name="{distress}" id="14476852" nSelect="0" countSub="5"><synset name="{anguish}" id="14449022" nSelect="0" countSub="0" /><synset name="{throe}" id="14477207" nSelect="0" countSub="0" /><synset name="{pressure}" id="14477076" nSelect="5" countSub="5" /></synset></synset></synset></synset></synset><synset name="{feeling}" id="26192" nSelect="0" countSub="0" /><synset name="{skillfulness}" id="5640433" nSelect="0" countSub="0" /><synset name="{cleavage}" id="13920012" nSelect="0" countSub="0" /><synset name="{medium}" id="13920169" nSelect="0" countSub="0" /><synset name="{ornamentation}" id="13920322" nSelect="0" countSub="0" /><synset name="{conditionality}" id="13924069" nSelect="0" countSub="0" /><synset name="{ground state}" id="13924196" nSelect="0" countSub="0" /><synset name="{nationhood}" id="13926451" nSelect="0" countSub="0" /><synset name="{relationship}" id="13928388" nSelect="0" countSub="0" /><synset name="{relationship}" id="13928668" nSelect="0" countSub="0" /><synset name="{tribalism}" id="13928943" nSelect="0" countSub="0" /><synset name="{utopia}" id="13932045" nSelect="0" countSub="0" /><synset name="{dystopia}" id="13932213" nSelect="0" countSub="0" /><synset name="{wild, natural state, state of nature}" id="13939353" nSelect="0" countSub="0" /><synset name="{isomerism}" id="13939734" nSelect="0" countSub="0" /><synset name="{degree, level, stage, point}" id="13939892" nSelect="0" countSub="0" /><synset name="{office, power}" id="13945102" nSelect="0" countSub="0" /><synset name="{status, position}" id="13945919" nSelect="0" countSub="0" /><synset name="{being, beingness, existence}" id="13954253" nSelect="0" countSub="0" /><synset name="{nonbeing}" id="13959818" nSelect="0" countSub="0" /><synset name="{death}" id="13962498" nSelect="0" countSub="0" /><synset name="{employment, employ}" id="13968092" nSelect="0" countSub="0" /><synset name="{unemployment}" id="13968308" nSelect="0" countSub="0" /><synset name="{order}" id="13968547" nSelect="0" countSub="0" /><synset name="{disorder}" id="13972797" nSelect="0" countSub="0" /><synset name="{hostility, enmity, antagonism}" id="13980288" nSelect="0" countSub="0" /><synset name="{conflict}" id="13980845" nSelect="0" countSub="0" /><synset name="{illumination}" id="13983147" nSelect="0" countSub="0" /><synset name="{freedom}" id="13991823" nSelect="0" countSub="0" /><synset name="{representation, delegacy, agency}" id="14000403" nSelect="0" countSub="0" /><synset name="{dependence, dependance, dependency}" id="14001348" nSelect="0" countSub="0" /><synset name="{motion}" id="14004317" nSelect="0" countSub="0" /><synset name="{motionlessness, stillness, lifelessness}" id="14006179" nSelect="0" countSub="0" /><synset name="{dead letter, non-issue}" id="14006821" nSelect="0" countSub="0" /><synset name="{action, activity, activeness}" id="14006945" nSelect="0" countSub="0" /><synset name="{inaction, inactivity, inactiveness}" id="14010148" nSelect="0" countSub="0" /><synset name="{temporary state}" id="14015731" nSelect="0" countSub="0" /><synset name="{imminence, imminency, imminentness, impendence, impendency, forthcomingness}" id="14030820" nSelect="0" countSub="0" /><synset name="{readiness, preparedness, preparation}" id="14031108" nSelect="0" countSub="0" /><synset name="{flux, state of flux}" id="14033917" nSelect="0" countSub="0" /><synset name="{kalemia}" id="14270016" nSelect="0" countSub="0" /><synset name="{enlargement}" id="14315071" nSelect="0" countSub="0" /><synset name="{separation}" id="14414294" nSelect="0" countSub="0" /><synset name="{union, unification}" id="14418395" nSelect="0" countSub="0" /><synset name="{maturity, matureness}" id="14424780" nSelect="0" countSub="0" /><synset name="{immaturity, immatureness}" id="14425974" nSelect="0" countSub="0" /><synset name="{grace, saving grace, state of grace}" id="14458181" nSelect="0" countSub="0" /><synset name="{damnation, eternal damnation}" id="14458593" nSelect="0" countSub="0" /><synset name="{omniscience}" id="14458943" nSelect="0" countSub="0" /><synset name="{omnipotence}" id="14459185" nSelect="0" countSub="0" /><synset name="{perfection, flawlessness, ne plus ultra}" id="14459422" nSelect="0" countSub="0" /><synset name="{integrity, unity, wholeness}" id="14460565" nSelect="0" countSub="0" /><synset name="{imperfection, imperfectness}" id="14462666" nSelect="0" countSub="0" /><synset name="{receivership}" id="14479320" nSelect="0" countSub="0" /><synset name="{ownership}" id="14479488" nSelect="0" countSub="0" /><synset name="{obligation}" id="14490110" nSelect="0" countSub="0" /><synset name="{end, destruction, death}" id="14562960" nSelect="0" countSub="0" /><synset name="{revocation, annulment}" id="14564056" nSelect="0" countSub="0" /><synset name="{merchantability}" id="14564165" nSelect="0" countSub="0" /><synset name="{turgor}" id="14568762" nSelect="0" countSub="0" /><synset name="{homozygosity}" id="14569337" nSelect="0" countSub="0" /><synset name="{heterozygosity}" id="14569508" nSelect="0" countSub="0" /><synset name="{neotony}" id="14569683" nSelect="0" countSub="0" /><synset name="{plurality}" id="14569844" nSelect="0" countSub="0" /><synset name="{polyvalence, polyvalency}" id="14570091" nSelect="0" countSub="0" /><synset name="{polyvalence, polyvalency, multivalence, multivalency}" id="14570330" nSelect="0" countSub="0" /><synset name="{paternity}" id="14578792" nSelect="0" countSub="0" /><synset name="{utilization}" id="14580476" nSelect="0" countSub="0" /><synset name="{situation, state of affairs}" id="13927383" nSelect="4" countSub="4"><synset name="{absurd, the absurd}" id="13928191" nSelect="0" countSub="0" /><synset name="{acceptance}" id="13932421" nSelect="0" countSub="0" /><synset name="{ballgame, new ballgame}" id="13932739" nSelect="0" countSub="0" /><synset name="{challenge}" id="13932948" nSelect="0" countSub="0" /><synset name="{childlessness}" id="13933103" nSelect="0" countSub="0" /><synset name="{complication}" id="13933221" nSelect="0" countSub="0" /><synset name="{crowding}" id="13933841" nSelect="0" countSub="0" /><synset name="{disequilibrium}" id="13934274" nSelect="0" countSub="0" /><synset name="{element}" id="13934465" nSelect="0" countSub="0" /><synset name="{environment}" id="13934596" nSelect="0" countSub="0" /><synset name="{equilibrium}" id="13934900" nSelect="0" countSub="0" /><synset name="{exclusion}" id="13935227" nSelect="0" countSub="0" /><synset name="{goldfish bowl, fish bowl, fishbowl}" id="13935400" nSelect="0" countSub="0" /><synset name="{hotbed}" id="13935753" nSelect="0" countSub="0" /><synset name="{inclusion}" id="13936304" nSelect="0" countSub="0" /><synset name="{intestacy}" id="13936441" nSelect="0" countSub="0" /><synset name="{picture, scene}" id="13937075" nSelect="0" countSub="0" /><synset name="{prison, prison house}" id="13937284" nSelect="0" countSub="0" /><synset name="{rejection}" id="13937554" nSelect="0" countSub="0" /><synset name="{size, size of it}" id="13937727" nSelect="0" countSub="0" /><synset name="{square one}" id="13937918" nSelect="0" countSub="0" /><synset name="{status quo}" id="13938210" nSelect="0" countSub="0" /><synset name="{thing}" id="13943968" nSelect="0" countSub="0" /></synset></synset></synset></synset><synset name="{physical entity}" id="1930" nSelect="0" countSub="44"><synset name="{object, physical object}" id="2684" nSelect="0" countSub="29"><synset name="{location}" id="27167" nSelect="0" countSub="14"><synset name="{region}" id="8630985" nSelect="0" countSub="5"><synset name="{geographical area, geographic area, geographical region, geographic region}" id="8574314" nSelect="0" countSub="5"><synset name="{wilderness, wild}" id="8683548" nSelect="0" countSub="5"><synset name="{barren, waste, wasteland}" id="8504594" nSelect="0" countSub="0" /><synset name="{bush}" id="8505018" nSelect="0" countSub="0" /><synset name="{frontier}" id="8505402" nSelect="5" countSub="5" /></synset></synset></synset><synset name="{here}" id="8489497" nSelect="0" countSub="0" /><synset name="{there}" id="8489627" nSelect="0" countSub="0" /><synset name="{somewhere}" id="8489765" nSelect="0" countSub="0" /><synset name="{bilocation}" id="8489890" nSelect="0" countSub="0" /><synset name="{seat}" id="8490039" nSelect="0" countSub="0" /><synset name="{home}" id="8490199" nSelect="0" countSub="0" /><synset name="{base, home}" id="8490402" nSelect="0" countSub="0" /><synset name="{outer space, space}" id="8500433" nSelect="0" countSub="0" /><synset name="{jungle}" id="8509111" nSelect="0" countSub="0" /><synset name="{northeast}" id="8561230" nSelect="0" countSub="0" /><synset name="{east}" id="8561351" nSelect="0" countSub="0" /><synset name="{southeast}" id="8561462" nSelect="4" countSub="4" /><synset name="{south}" id="8561583" nSelect="0" countSub="0" /><synset name="{southwest}" id="8561714" nSelect="0" countSub="0" /><synset name="{west}" id="8561835" nSelect="0" countSub="0" /><synset name="{northwest}" id="8561946" nSelect="0" countSub="0" /><synset name="{Earth, earth}" id="8562067" nSelect="0" countSub="0" /><synset name="{line}" id="8593262" nSelect="0" countSub="0" /><synset name="{point}" id="8620061" nSelect="0" countSub="0" /><synset name="{region, part}" id="8630039" nSelect="0" countSub="0" /><synset name="{whereabouts}" id="8683383" nSelect="0" countSub="0" /><synset name="{sodom}" id="8795880" nSelect="0" countSub="0" /><synset name="{pass, mountain pass, notch}" id="9386842" nSelect="0" countSub="0" /><synset name="{space}" id="13910384" nSelect="0" countSub="0" /><synset name="{north}" id="8561081" nSelect="5" countSub="5" /></synset><synset name="{whole, unit}" id="3553" nSelect="0" countSub="15"><synset name="{living thing, animate thing}" id="4258" nSelect="0" countSub="15"><synset name="{organism, being}" id="4475" nSelect="0" countSub="15"><synset name="{person, individual, someone, somebody, mortal, soul}" id="7846" nSelect="0" countSub="15"><synset name="{communicator}" id="9610660" nSelect="0" countSub="7"><synset name="{negotiator, negotiant, treater}" id="10351874" nSelect="0" countSub="7"><synset name="{representative}" id="10522035" nSelect="0" countSub="7"><synset name="{head of state, chief of state}" id="10164747" nSelect="0" countSub="7"><synset name="{Prime Minister, PM, premier}" id="9907196" nSelect="0" countSub="0" /><synset name="{president}" id="10467179" nSelect="0" countSub="0" /><synset name="{President of the United States, United States President, President, Chief Executive}" id="10467395" nSelect="0" countSub="0" /><synset name="{sovereign, crowned head, monarch}" id="10628644" nSelect="0" countSub="0" /><synset name="{chancellor, premier, prime minister}" id="9906986" nSelect="7" countSub="7"><synset name="{taoiseach}" id="10691052" nSelect="0" countSub="0" /></synset></synset></synset></synset></synset><synset name="{warrior}" id="10768585" nSelect="0" countSub="4"><synset name="{brave}" id="9645788" nSelect="0" countSub="0" /><synset name="{centurion}" id="9905050" nSelect="0" countSub="0" /><synset name="{Crusader}" id="9981365" nSelect="0" countSub="0" /><synset name="{samurai}" id="10549763" nSelect="0" countSub="0" /><synset name="{guerrilla, guerilla, irregular, insurgent}" id="10150556" nSelect="4" countSub="4"><synset name="{Maquis, Maquisard}" id="10292824" nSelect="0" countSub="0" /><synset name="{urban guerrilla}" id="10741258" nSelect="0" countSub="0" /></synset></synset><synset name="{leader}" id="9623038" nSelect="0" countSub="4"><synset name="{head, chief, top dog}" id="10162991" nSelect="0" countSub="4"><synset name="{administrator, decision maker}" id="9770949" nSelect="0" countSub="4"><synset name="{executive, executive director}" id="10069645" nSelect="0" countSub="4"><synset name="{corporate executive, business executive}" id="9966255" nSelect="0" countSub="0" /><synset name="{minister, government minister}" id="10320863" nSelect="0" countSub="0" /><synset name="{rainmaker}" id="10505459" nSelect="0" countSub="0" /><synset name="{Surgeon General}" id="10679610" nSelect="0" countSub="0" /><synset name="{vice president, V.P.}" id="10751265" nSelect="4" countSub="4"><synset name="{executive vice president}" id="10070108" nSelect="0" countSub="0" /><synset name="{senior vice president}" id="10579549" nSelect="0" countSub="0" /><synset name="{Vice President of the United States}" id="10751527" nSelect="0" countSub="0" /></synset></synset></synset></synset></synset></synset></synset></synset></synset></synset><synset name="{causal agent, cause, causal agency}" id="7347" nSelect="0" countSub="15"><synset name="{person, individual, someone, somebody, mortal, soul}" id="7846" nSelect="0" countSub="15"><synset name="{communicator}" id="9610660" nSelect="0" countSub="7"><synset name="{negotiator, negotiant, treater}" id="10351874" nSelect="0" countSub="7"><synset name="{representative}" id="10522035" nSelect="0" countSub="7"><synset name="{head of state, chief of state}" id="10164747" nSelect="0" countSub="7"><synset name="{Prime Minister, PM, premier}" id="9907196" nSelect="0" countSub="0" /><synset name="{president}" id="10467179" nSelect="0" countSub="0" /><synset name="{President of the United States, United States President, President, Chief Executive}" id="10467395" nSelect="0" countSub="0" /><synset name="{sovereign, crowned head, monarch}" id="10628644" nSelect="0" countSub="0" /><synset name="{chancellor, premier, prime minister}" id="9906986" nSelect="7" countSub="7"><synset name="{taoiseach}" id="10691052" nSelect="0" countSub="0" /></synset></synset></synset></synset></synset><synset name="{warrior}" id="10768585" nSelect="0" countSub="4"><synset name="{brave}" id="9645788" nSelect="0" countSub="0" /><synset name="{centurion}" id="9905050" nSelect="0" countSub="0" /><synset name="{Crusader}" id="9981365" nSelect="0" countSub="0" /><synset name="{samurai}" id="10549763" nSelect="0" countSub="0" /><synset name="{guerrilla, guerilla, irregular, insurgent}" id="10150556" nSelect="4" countSub="4"><synset name="{Maquis, Maquisard}" id="10292824" nSelect="0" countSub="0" /><synset name="{urban guerrilla}" id="10741258" nSelect="0" countSub="0" /></synset></synset><synset name="{leader}" id="9623038" nSelect="0" countSub="4"><synset name="{head, chief, top dog}" id="10162991" nSelect="0" countSub="4"><synset name="{administrator, decision maker}" id="9770949" nSelect="0" countSub="4"><synset name="{executive, executive director}" id="10069645" nSelect="0" countSub="4"><synset name="{corporate executive, business executive}" id="9966255" nSelect="0" countSub="0" /><synset name="{minister, government minister}" id="10320863" nSelect="0" countSub="0" /><synset name="{rainmaker}" id="10505459" nSelect="0" countSub="0" /><synset name="{Surgeon General}" id="10679610" nSelect="0" countSub="0" /><synset name="{vice president, V.P.}" id="10751265" nSelect="4" countSub="4"><synset name="{executive vice president}" id="10070108" nSelect="0" countSub="0" /><synset name="{senior vice president}" id="10579549" nSelect="0" countSub="0" /><synset name="{Vice President of the United States}" id="10751527" nSelect="0" countSub="0" /></synset></synset></synset></synset></synset></synset></synset></synset></synset><synset name="{Iraq, Republic of Iraq, Al-Iraq, Irak}" id="8913434" nSelect="1" countSub="1" /></synset></root>
